README.md
setup.py
zi_i18n/__init__.py
zi_i18n/i18n.py
zi_i18n/object.py
zi_i18n/test.py
zi_i18n.egg-info/PKG-INFO
zi_i18n.egg-info/SOURCES.txt
zi_i18n.egg-info/dependency_links.txt
zi_i18n.egg-info/top_level.txt