Metadata-Version: 2.1
Name: zi-i18n
Version: 0.0.8
Summary: A Experimental Internationalization System
Home-page: https://github.com/null2264/i18n
Author: null2264
Author-email: 
License: GPL GNU-3.0
Platform: UNKNOWN
